README.md
setup.cfg
setup.py
streamfieldutils/__init__.py
streamfieldutils/iterators.py
tests/__init__.py
tests/conftest.py
tests/settings.py
tests/test_iterator.py
tests/testapp/__init__.py
tests/testapp/blocks.py
tests/testapp/models.py
tests/testapp/migrations/0001_initial.py
tests/testapp/migrations/__init__.py
wagtail_streamfield_migrate.egg-info/PKG-INFO
wagtail_streamfield_migrate.egg-info/SOURCES.txt
wagtail_streamfield_migrate.egg-info/dependency_links.txt
wagtail_streamfield_migrate.egg-info/requires.txt
wagtail_streamfield_migrate.egg-info/top_level.txt