Metadata-Version: 2.1
Name: wagtail-streamfield-migrate
Version: 0.0.1
Summary: Wagtail utilities for streamfields
Home-page: https://github.com/mikemonteith/wagtail-streamfield-utils
Author: Mike Monteith
Author-email: <mike.monteith@nhs.net>
License: UNKNOWN
Platform: UNKNOWN
Provides-Extra: testing
